content_safety_text/__init__.py
content_safety_text/tools/__init__.py
content_safety_text/tools/content_safety_text_tool.py
content_safety_text/tools/utils.py
content_safety_text/yamls/content_safety_text_tool.yaml
tests/__init__.py
tests/test_content_safety_text_tool.py
promptflow_contentsafety-0.0.9.dist-info/METADATA
promptflow_contentsafety-0.0.9.dist-info/WHEEL
promptflow_contentsafety-0.0.9.dist-info/entry_points.txt
promptflow_contentsafety-0.0.9.dist-info/top_level.txt
promptflow_contentsafety-0.0.9.dist-info/RECORD
