Metadata-Version: 2.1
Name: promptflow-contentsafety
Version: 0.0.9
Summary: This is a contentsafety tool package used for prompt flow
